odoo/addons/shopinvader_product_template_tags/README.rst
odoo/addons/shopinvader_product_template_tags/__init__.py
odoo/addons/shopinvader_product_template_tags/__manifest__.py
odoo/addons/shopinvader_product_template_tags/data/ir_export_product.xml
odoo/addons/shopinvader_product_template_tags/i18n/shopinvader_product_template_tags.pot
odoo/addons/shopinvader_product_template_tags/readme/CONTRIBUTORS.rst
odoo/addons/shopinvader_product_template_tags/readme/DESCRIPTION.rst
odoo/addons/shopinvader_product_template_tags/static/description/index.html
odoo14_addon_shopinvader_product_template_tags-14.0.1.0.1.dev3.dist-info/METADATA
odoo14_addon_shopinvader_product_template_tags-14.0.1.0.1.dev3.dist-info/WHEEL
odoo14_addon_shopinvader_product_template_tags-14.0.1.0.1.dev3.dist-info/top_level.txt
odoo14_addon_shopinvader_product_template_tags-14.0.1.0.1.dev3.dist-info/RECORD
